{
    "strikes": [
        {
            "id": 1,
            "attacker": "Россия",
            "attacker_region": "Тульская область",
            "attacker_id": "1037028831606865970",
            "target": "Украина",
            "target_region": "м. Київ",
            "target_type": "Гражданские фабрики",
            "weapon": "Ударные БПЛА",
            "weapon_id": "drones",
            "quantity": 400,
            "intercepted": 233,
            "surviving": 167,
            "hits": 85,
            "destroyed": 85,
            "casualties": 0,
            "fuel_losses": {},
            "distance": 636,
            "timestamp": "2026-03-12 20:56:46.102599"
        },
        {
            "id": 2,
            "attacker": "Россия",
            "attacker_region": "Чеченская Республика",
            "attacker_id": "1037028831606865970",
            "target": "Украина",
            "target_region": "Київська область",
            "target_type": "ЦОД",
            "weapon": "Баллистические ракеты",
            "weapon_id": "ballistic_missiles",
            "quantity": 850,
            "intercepted": 168,
            "surviving": 682,
            "hits": 98,
            "destroyed": 98,
            "casualties": 0,
            "fuel_losses": {},
            "distance": 1391,
            "timestamp": "2026-03-12 20:58:06.322386"
        },
        {
            "id": 3,
            "attacker": "Россия",
            "attacker_region": "Республика Крым",
            "attacker_id": "1037028831606865970",
            "target": "Украина",
            "target_region": "Дніпропетровська область",
            "target_type": "Офисные центры",
            "weapon": "Разведывательные БПЛА",
            "weapon_id": "recon_uav",
            "quantity": 500,
            "intercepted": 312,
            "surviving": 188,
            "hits": 32,
            "destroyed": 32,
            "casualties": 0,
            "fuel_losses": {},
            "distance": 368,
            "timestamp": "2026-03-12 21:00:48.917962"
        },
        {
            "id": 4,
            "attacker": "Россия",
            "attacker_region": "Республика Дагестан",
            "attacker_id": "1037028831606865970",
            "target": "Украина",
            "target_region": "Львівська область",
            "target_type": "ЦОД",
            "weapon": "Крылатые ракеты",
            "weapon_id": "cruise_missiles",
            "quantity": 2200,
            "intercepted": 762,
            "surviving": 1438,
            "hits": 68,
            "destroyed": 68,
            "casualties": 0,
            "fuel_losses": {},
            "distance": 1944,
            "timestamp": "2026-03-12 21:02:23.899674"
        },
        {
            "id": 5,
            "attacker": "Украина",
            "attacker_region": "Харківська область",
            "attacker_id": "1056458599045541890",
            "target": "Россия",
            "target_region": "Чеченская Республика",
            "target_type": "ЦОД",
            "weapon": "Крылатые ракеты",
            "weapon_id": "cruise_missiles",
            "quantity": 50,
            "intercepted": 22,
            "surviving": 28,
            "hits": 22,
            "destroyed": 22,
            "casualties": 0,
            "fuel_losses": {},
            "distance": 1028,
            "timestamp": "2026-03-12 21:03:29.637781"
        },
        {
            "id": 6,
            "attacker": "Украина",
            "attacker_region": "Полтавська область",
            "attacker_id": "1056458599045541890",
            "target": "Россия",
            "target_region": "Республика Калмыкия",
            "target_type": "Нефтебазы",
            "weapon": "Баллистические ракеты",
            "weapon_id": "ballistic_missiles",
            "quantity": 10,
            "intercepted": 1,
            "surviving": 9,
            "hits": 2,
            "destroyed": 2,
            "casualties": 132,
            "fuel_losses": {
                "oil": 2.580818373511825,
                "gas": 1.8244867544407906
            },
            "distance": 810,
            "timestamp": "2026-03-12 21:51:28.263536"
        }
    ],
    "stats": {}
}